{"errors": [{"src": "/Users/kiwi/projects/qualimetrics/share/examples/sdc/common/input.adb", "rule_key": "MINOR__CHECK__overflow check", "directory": "common", "line": "69", "msg": "overflow check might fail: requires Col <= 2**31-2\"", "prj": "Sdc"}, {"src": "/Users/kiwi/projects/qualimetrics/share/examples/sdc/common/input.adb", "rule_key": "MAJOR__CHECK__array index check", "directory": "common", "line": "110", "msg": "array index check might fail: requires First_Char <= 1_024\"", "prj": "Sdc"}, {"src": "/Users/kiwi/projects/qualimetrics/share/examples/sdc/common/input.adb", "rule_key": "MAJOR__CHECK__array index check", "directory": "common", "line": "191", "msg": "array index check might fail: requires First_Char <= 1_024\"", "prj": "Sdc"}, {"src": "/Users/kiwi/projects/qualimetrics/share/examples/sdc/common/input.adb", "rule_key": "MINOR__CHECK__validity check", "directory": "common", "line": "202", "msg": "validity check: S(I) might be uninitialized\"", "prj": "Sdc"}, {"src": "/Users/kiwi/projects/qualimetrics/share/examples/sdc/common/input.adb", "rule_key": "MAJOR__CHECK__precondition", "directory": "common", "line": "260", "msg": "precondition might fail on input.get_char: requires First_Char <= Last_Char or Line_Num <= 2**31-2\"", "prj": "Sdc"}, {"src": "/Users/kiwi/projects/qualimetrics/share/examples/sdc/common/sdc.adb", "rule_key": "MAJOR__WARNING__loop does not terminate", "directory": "common", "line": "28", "msg": "loop does not terminate\"", "prj": "Sdc"}, {"src": "/Users/kiwi/projects/qualimetrics/share/examples/sdc/common/sdc.adb", "rule_key": "MAJOR__CHECK__precondition", "directory": "common", "line": "30", "msg": "precondition might fail on tokens.process: requires T.Kind /= Op or T.Op in range\"", "prj": "Sdc"}, {"src": "/Users/kiwi/projects/qualimetrics/share/examples/sdc/common/sdc.adb", "rule_key": "MAJOR__CHECK__precondition", "directory": "common", "line": "30", "msg": "precondition might fail on tokens.process: requires T.Kind <= Op or T.Instr <= Print\"", "prj": "Sdc"}, {"src": "/Users/kiwi/projects/qualimetrics/share/examples/sdc/common/sdc.adb", "rule_key": "MAJOR__CHECK__precondition", "directory": "common", "line": "30", "msg": "precondition might fail on tokens.process: requires T.Kind >= Op or Last in (2..199 | 201)\"", "prj": "Sdc"}, {"src": "/Users/kiwi/projects/qualimetrics/share/examples/sdc/common/stack.adb", "rule_key": "MAJOR__WARNING__suspicious precondition", "directory": "common", "line": "41", "msg": "suspicious precondition for Last: not a contiguous range of values\"", "prj": "Sdc"}, {"src": "/Users/kiwi/projects/qualimetrics/share/examples/sdc/struct/instructions.adb", "rule_key": "MINOR__CHECK__conditional check", "directory": "struct", "line": "29", "msg": "conditional check might raise exception: checking that I < (quit)\"", "prj": "Sdc"}, {"src": "/Users/kiwi/projects/qualimetrics/share/examples/sdc/struct/tokens.adb", "rule_key": "MAJOR__CHECK__array index check", "directory": "struct", "line": "28", "msg": "array index check might fail: requires (Input.Next_Word)'First <= (Input.Next_Word)'First and (Input.Next_Word)'First <= (Input.Next_Word)'Last\"", "prj": "Sdc"}, {"src": "/Users/kiwi/projects/qualimetrics/share/examples/sdc/struct/tokens.adb", "rule_key": "MINOR__CHECK__validity check", "directory": "struct", "line": "28", "msg": "validity check: Word.all((Input.Next_Word)'First) might be uninitialized\"", "prj": "Sdc"}, {"src": "/Users/kiwi/projects/qualimetrics/share/examples/sdc/struct/values.adb", "rule_key": "MAJOR__WARNING__suspicious precondition", "directory": "struct", "line": "11", "msg": "suspicious precondition for Last: not a contiguous range of values\"", "prj": "Sdc"}]}